vital_ai_aimp/__init__.py
vital_ai_aimp-0.1.1.dist-info/LICENSE
vital_ai_aimp-0.1.1.dist-info/METADATA
vital_ai_aimp-0.1.1.dist-info/WHEEL
vital_ai_aimp-0.1.1.dist-info/top_level.txt
vital_ai_aimp-0.1.1.dist-info/RECORD
