Metadata-Version: 2.1
Name: vital-ai-aimp
Version: 0.1.1
Summary: VitalSigns aimp domain
Home-page: https://github.com/vital-ai/vitalhome-aimp
Author: Marc Hadfield
Author-email: marc@vital.ai
License: Apache License 2.0
Classifier: Programming Language :: Python :: 3.12
Classifier: License :: OSI Approved :: Apache Software License
Classifier: Operating System :: OS Independent
Requires-Python: >=3.10
License-File: LICENSE
Requires-Dist: vital-ai-domain
